[
  {
    "job_title": "Solution Engineer, Customer Sales and Service, Federal and Government",
    "employer_name": "Microsoft",
    "job_city": "Redmond",
    "job_state": "WA",
    "job_description": "Join Microsoft to empower every person and organization on the planet.",
    "job_apply_link": "https://jobs.careers.microsoft.com/global/en/job/1873893",
    "job_posted_at_datetime_utc": "2025-09-15T01:43:53.652Z",
    "job_employment_type": "FULLTIME",
    "id": "microsoft-solution-engineer-customer-sales-and-service-federal-and-government-redmond"
  }
]