[
  {
    "job_title": "Software Development Engineer, AGI Information",
    "employer_name": "Amazon",
    "job_city": "Bellevue",
    "job_state": "WA",
    "job_description": "Basic qualifications:",
    "job_apply_link": "https://amazon.jobs/en-gb/jobs/3008940/software-development-engineer-agi-information",
    "job_posted_at": "2025-09-05T00:10:38.972Z",
    "job_posted_at_datetime_utc": "2025-09-05T00:10:38.972Z",
    "id": "amazon-software-development-engineer-agi-information-bellevue"
  },
  {
    "job_title": "Research Scientist Intern, Spatial Audio Capture and Reproduction (PhD)",
    "employer_name": "Meta",
    "job_city": "Multiple",
    "job_state": "Locations",
    "job_description": "Software Engineering",
    "job_apply_link": "https://www.metacareers.com/jobs/1633859934240924",
    "job_posted_at": "Recently",
    "job_posted_at_datetime_utc": "Recently",
    "id": "meta-research-scientist-intern-spatial-audio-capture-and-reproduction-phd-multiple"
  },
  {
    "job_title": "Research Scientist Intern, Hearing Science and Auditory Perception (PhD)",
    "employer_name": "Meta",
    "job_city": "Multiple",
    "job_state": "Locations",
    "job_description": "Software Engineering",
    "job_apply_link": "https://www.metacareers.com/jobs/759283353381235",
    "job_posted_at": "Recently",
    "job_posted_at_datetime_utc": "Recently",
    "id": "meta-research-scientist-intern-hearing-science-and-auditory-perception-phd-multiple"
  },
  {
    "job_title": "Senior Engineering Manager",
    "employer_name": "Microsoft",
    "job_city": "Redmond",
    "job_state": "WA",
    "job_description": "Join Microsoft to empower every person and organization on the planet.",
    "job_apply_link": "https://jobs.careers.microsoft.com/global/en/job/1872252",
    "job_posted_at_datetime_utc": "2025-09-05T16:17:20.854Z",
    "job_employment_type": "FULLTIME",
    "id": "microsoft-senior-engineering-manager-redmond"
  },
  {
    "job_title": "Sr. Engineering Group Ops Manager",
    "employer_name": "Microsoft",
    "job_city": "Redmond",
    "job_state": "WA",
    "job_description": "Join Microsoft to empower every person and organization on the planet.",
    "job_apply_link": "https://jobs.careers.microsoft.com/global/en/job/1872893",
    "job_posted_at_datetime_utc": "2025-09-05T16:17:20.854Z",
    "job_employment_type": "FULLTIME",
    "id": "microsoft-sr-engineering-group-ops-manager-redmond"
  },
  {
    "job_title": "Principal Sourcing Engineer - Devices",
    "employer_name": "Microsoft",
    "job_city": "Redmond",
    "job_state": "WA",
    "job_description": "Join Microsoft to empower every person and organization on the planet.",
    "job_apply_link": "https://jobs.careers.microsoft.com/global/en/job/1863874",
    "job_posted_at_datetime_utc": "2025-09-05T16:17:20.854Z",
    "job_employment_type": "FULLTIME",
    "id": "microsoft-principal-sourcing-engineer-devices-redmond"
  },
  {
    "job_title": "United States Managing Director, Solution Engineering - Cloud & AI",
    "employer_name": "Microsoft",
    "job_city": "Redmond",
    "job_state": "WA",
    "job_description": "Join Microsoft to empower every person and organization on the planet.",
    "job_apply_link": "https://jobs.careers.microsoft.com/global/en/job/1872891",
    "job_posted_at_datetime_utc": "2025-09-05T16:17:20.854Z",
    "job_employment_type": "FULLTIME",
    "id": "microsoft-united-states-managing-director-solution-engineering-cloud-ai-redmond"
  }
]