[
  {
    "job_title": "Principal Group Engineering Manager",
    "employer_name": "Microsoft",
    "job_city": "Redmond",
    "job_state": "WA",
    "job_description": "Join Microsoft to empower every person and organization on the planet.",
    "job_apply_link": "https://jobs.careers.microsoft.com/global/en/job/1863752",
    "job_posted_at_datetime_utc": "2025-09-02T13:23:25.014Z",
    "job_employment_type": "FULLTIME",
    "id": "microsoft-principal-group-engineering-manager-redmond"
  },
  {
    "job_title": "Junior Solution Engineer - AI & Apps | Presales",
    "employer_name": "Microsoft",
    "job_city": "Redmond",
    "job_state": "WA",
    "job_description": "Join Microsoft to empower every person and organization on the planet.",
    "job_apply_link": "https://jobs.careers.microsoft.com/global/en/job/1850565",
    "job_posted_at_datetime_utc": "2025-09-02T13:23:25.014Z",
    "job_employment_type": "FULLTIME",
    "id": "microsoft-junior-solution-engineer-ai-apps-presales-redmond"
  }
]